README
setup.cfg
setup.py
summa_visualization.egg-info/PKG-INFO
summa_visualization.egg-info/SOURCES.txt
summa_visualization.egg-info/dependency_links.txt
summa_visualization.egg-info/requires.txt
summa_visualization.egg-info/top_level.txt
visualization/__init__.py
visualization/export.py