Metadata-Version: 1.2
Name: summa-visualization
Version: 0.1.0b0
Summary: A visualization for the graphs generated by summa.
Home-page: https://github.com/summanlp/summa-visualization
Author: Federico Barrios, Federico Lopez
Author-email: summanlp@gmail.com
License: UNKNOWN
Download-URL: https://github.com/summanlp/summa-visualization/tarball/v0.1.0
Keywords: summa,nlp,summarization,NLP,natural language processing,automatic summarization,keywords,summary,textrank,pagerank,visualization,export
Platform: UNKNOWN
Classifier: Development Status :: 4 - Beta
Classifier: License :: OSI Approved :: MIT License
Classifier: Intended Audience :: Developers
Classifier: Intended Audience :: Education
Classifier: Topic :: Scientific/Engineering :: Information Analysis
Classifier: Topic :: Text Processing :: Linguistic
Classifier: Programming Language :: Python :: 2.7
Classifier: Programming Language :: Python :: 2 :: Only
Requires-Python: >=2.7, <3.0
